python_artifactory_dependency_confusion_patch/__init__.py
python_artifactory_dependency_confusion_patch/artifactory_service.py
python_artifactory_dependency_confusion_patch/lib_generator.py
python_artifactory_dependency_confusion_patch/main.py
python_artifactory_dependency_confusion_patch/notification_service.py
python_artifactory_dependency_confusion_patch/public_name_reserver.py
python_artifactory_dependency_confusion_patch/pypi_service.py
python_artifactory_dependency_confusion_patch/domain/artifactory_body.py
python_artifactory_dependency_confusion_patch/domain/library.py
python_artifactory_dependency_confusion_patch/lib_template/README.md
python_artifactory_dependency_confusion_patch/lib_template/__init__.py
python_artifactory_dependency_confusion_patch/lib_template/pyproject.toml
python_artifactory_dependency_confusion_patch-1.4.0.dist-info/LICENSE
python_artifactory_dependency_confusion_patch-1.4.0.dist-info/METADATA
python_artifactory_dependency_confusion_patch-1.4.0.dist-info/WHEEL
python_artifactory_dependency_confusion_patch-1.4.0.dist-info/top_level.txt
python_artifactory_dependency_confusion_patch-1.4.0.dist-info/RECORD
